flashpolicies/__init__.py
flashpolicies/policies.py
flashpolicies/views.py
django_flashpolicies-1.14.dist-info/LICENSE
django_flashpolicies-1.14.dist-info/METADATA
django_flashpolicies-1.14.dist-info/WHEEL
django_flashpolicies-1.14.dist-info/top_level.txt
django_flashpolicies-1.14.dist-info/RECORD
